Metadata-Version: 2.1
Name: openwid
Version: 0.1.1
Summary: OpenWeather in Dash
Home-page: https://github.com/tolgahancepel/openwid
Author: Tolgahan Cepel
Author-email: tolgahan.cepel@gmail.com
License: UNKNOWN
Platform: UNKNOWN
Classifier: Programming Language :: Python :: 3
Classifier: License :: OSI Approved :: MIT License
Classifier: Operating System :: OS Independent
Classifier: Framework :: Dash
